dlmml/__init__.py
dlmml/parser/__init__.py
dlmml/parser/python/__init__.py
dlmml/parser/python/keras/__init__.py
dlmml/parser/python/keras/imports.py
dlmml/parser/python/keras/init.py
dlmml/parser/python/keras/inputs.py
dlmml/parser/python/keras/layers.py
dlmml/parser/python/keras/main.py
dlmml/parser/python/keras/symbol_table.py
dlmml/parser/python/keras/test_model.py
dlmml/parser/python/keras/train_pipeline.py
dlmml/parser/python/keras/visualize.py
dlmml/parser/python/keras/write.py
dlmml/utils/__init__.py
dlmml/utils/h5_to_json.py
dlmml/utils/json_to_dict.py
dlmml-0.0.3.dist-info/LICENSE
dlmml-0.0.3.dist-info/METADATA
dlmml-0.0.3.dist-info/WHEEL
dlmml-0.0.3.dist-info/top_level.txt
dlmml-0.0.3.dist-info/RECORD
