Metadata-Version: 2.1
Name: dlmml
Version: 0.0.3
Summary: Converts IR to Code. Heart of Auto-DL
Home-page: https://github.com/Auto-DL/DLMML
Author: Auto-DL
License: UNKNOWN
Platform: UNKNOWN
Classifier: Programming Language :: Python :: 3
Classifier: License :: OSI Approved :: GNU General Public License v3 (GPLv3)
Classifier: Operating System :: OS Independent
Requires-Python: >=3.6
License-File: LICENSE
